blue_rover/README.py
blue_rover/__init__.py
blue_rover/__main__.py
blue_rover/config.env
blue_rover/env.py
blue_rover/host.py
blue_rover/logger.py
blue_rover/sample.env
blue_rover/urls.py
blue_rover/.abcli/abcli.sh
blue_rover/.abcli/actions.sh
blue_rover/.abcli/aka.sh
blue_rover/.abcli/alias.sh
blue_rover/.abcli/blue_rover.sh
blue_rover/.abcli/browse.sh
blue_rover/.abcli/install.sh
blue_rover/.abcli/tests/README.sh
blue_rover/.abcli/tests/help.sh
blue_rover/.abcli/tests/version.sh
blue_rover/help/__init__.py
blue_rover/help/__main__.py
blue_rover/help/functions.py
blue_rover-4.51.1.dist-info/LICENSE
blue_rover-4.51.1.dist-info/METADATA
blue_rover-4.51.1.dist-info/WHEEL
blue_rover-4.51.1.dist-info/top_level.txt
blue_rover-4.51.1.dist-info/RECORD
